pycodemetrics/__init__.py
pycodemetrics/__main__.py
pycodemetrics/cli/__init__.py
pycodemetrics/cli/cli.py
pycodemetrics/cli/display_util.py
pycodemetrics/cli/exporter.py
pycodemetrics/cli/sandbox.py
pycodemetrics/cli/analyze_committer/cli.py
pycodemetrics/cli/analyze_committer/handler.py
pycodemetrics/cli/analyze_hotspot/cli.py
pycodemetrics/cli/analyze_hotspot/handler.py
pycodemetrics/cli/analyze_python/__init__.py
pycodemetrics/cli/analyze_python/cli.py
pycodemetrics/cli/analyze_python/handler.py
pycodemetrics/config/__init__.py
pycodemetrics/config/config_manager.py
pycodemetrics/gitclient/__init__.py
pycodemetrics/gitclient/gitcli.py
pycodemetrics/gitclient/gitlog_parser.py
pycodemetrics/gitclient/models.py
pycodemetrics/metrics/__init__.py
pycodemetrics/metrics/changecount.py
pycodemetrics/metrics/hotspot.py
pycodemetrics/metrics/py/cognitive_complexity.py
pycodemetrics/metrics/py/import_analyzer.py
pycodemetrics/metrics/py/python_metrics.py
pycodemetrics/metrics/py/raw/__init__.py
pycodemetrics/metrics/py/raw/cc_wrapper.py
pycodemetrics/metrics/py/raw/radon_wrapper.py
pycodemetrics/services/__init__.py
pycodemetrics/services/analyze_committer.py
pycodemetrics/services/analyze_hotspot.py
pycodemetrics/services/analyze_python_metrics.py
pycodemetrics/util/__init__.py
pycodemetrics/util/file_util.py
pycodemetrics-0.0.13.dist-info/METADATA
pycodemetrics-0.0.13.dist-info/WHEEL
pycodemetrics-0.0.13.dist-info/entry_points.txt
pycodemetrics-0.0.13.dist-info/licenses/LICENSE
pycodemetrics-0.0.13.dist-info/RECORD
